llava_caption/__init__.py
llava_caption/cli.py
llava_caption/config.py
llava_caption/models/__init__.py
llava_caption/models/base.py
llava_caption/models/dual.py
llava_caption/models/huggingface.py
llava_caption/models/llama_cpp.py
llava_caption/models/mlx.py
llava_caption/models/ollama.py
llava_caption/models/vision.py
llava_caption/utils/__init__.py
llava_caption/utils/image.py
llava_caption/utils/text.py
llava_caption-0.8.0.dist-info/LICENSE
llava_caption-0.8.0.dist-info/METADATA
llava_caption-0.8.0.dist-info/WHEEL
llava_caption-0.8.0.dist-info/RECORD
