Metadata-Version: 2.3
Name: llava-caption
Version: 0.8.0
Summary: Automatically caption images using various LLaVA multimodal models. This tool processes images with state-of-the-art vision language models to generate accurate, high-quality captions.
License: GPL3
Author: David Van de Ven
Author-email: zanshin.g1@gmail.com
Requires-Python: >=3.13,<4
Classifier: License :: Other/Proprietary License
Classifier: Programming Language :: Python :: 3
Classifier: Programming Language :: Python :: 3.13
Requires-Dist: Pillow
Requires-Dist: httpx
Requires-Dist: huggingface-hub
Requires-Dist: json-repair
Requires-Dist: llama-cpp-python
Requires-Dist: mlx
Requires-Dist: mlx-vlm
Requires-Dist: ollama
Requires-Dist: pandas
Requires-Dist: requests (>=2.32.3,<3.0.0)
Requires-Dist: torch
Requires-Dist: tqdm
Requires-Dist: transformers
Project-URL: Issues, https://github.com/Zanshinmu/llava-caption/issues
Project-URL: Repository, https://github.com/Zanshinmu/llava-caption
